{
  "annotations": {
    "list": [
      {
        "builtIn": 1,
        "datasource": "-- Grafana --",
        "enable": true,
        "hide": true,
        "iconColor": "rgba(0, 211, 255, 1)",
        "name": "Annotations & Alerts",
        "type": "dashboard"
      }
    ]
  },
  "editable": true,
  "gnetId": null,
  "graphTooltip": 0,
  "id": 2,
  "links": [],
  "panels": [
    {
      "aliasColors": {},
      "bars": false,
      "dashLength": 10,
      "dashes": false,
      "datasource": "Prometheus",
      "fieldConfig": {
        "defaults": {
          "custom": {}
        },
        "overrides": []
      },
      "fill": 1,
      "fillGradient": 0,
      "gridPos": {
        "h": 10,
        "w": 20,
        "x": 0,
        "y": 0
      },
      "hiddenSeries": false,
      "id": 13,
      "legend": {
        "alignAsTable": true,
        "avg": true,
        "current": false,
        "max": true,
        "min": true,
        "show": true,
        "total": false,
        "values": true
      },
      "lines": true,
      "linewidth": 1,
      "nullPointMode": "null",
      "options": {
        "alertThreshold": true
      },
      "percentage": false,
      "pluginVersion": "7.3.6",
      "pointradius": 2,
      "points": false,
      "renderer": "flot",
      "seriesOverrides": [],
      "spaceLength": 10,
      "stack": false,
      "steppedLine": false,
      "targets": [
        {
          "expr": "histogram_quantile(0.99, sum(rate(awareness_carbon_estimate_calls_timer_bucket{job=\"carbonawareness\", client=\"webapi\"}[$__range])) by (le))",
          "interval": "",
          "legendFormat": "Web API",
          "refId": "A"
        },
        {
          "expr": "histogram_quantile(0.99, sum(rate(awareness_carbon_estimate_calls_timer_bucket{job=\"carbonawareness\", client=\"grpc\"}[$__range])) by (le))",
          "interval": "",
          "legendFormat": "gRPC",
          "refId": "C"
        }
      ],
      "thresholds": [],
      "timeFrom": null,
      "timeRegions": [],
      "timeShift": null,
      "title": "Clients request duration p=0.99",
      "tooltip": {
        "shared": true,
        "sort": 0,
        "value_type": "individual"
      },
      "type": "graph",
      "xaxis": {
        "buckets": null,
        "mode": "time",
        "name": null,
        "show": true,
        "values": []
      },
      "yaxes": [
        {
          "format": "short",
          "label": null,
          "logBase": 1,
          "max": null,
          "min": null,
          "show": true
        },
        {
          "format": "short",
          "label": null,
          "logBase": 1,
          "max": null,
          "min": null,
          "show": true
        }
      ],
      "yaxis": {
        "align": false,
        "alignLevel": null
      }
    },
    {
      "datasource": null,
      "description": "",
      "fieldConfig": {
        "defaults": {
          "custom": {},
          "mappings": [],
          "thresholds": {
            "mode": "absolute",
            "steps": [
              {
                "color": "green",
                "value": null
              },
              {
                "color": "red",
                "value": 80
              }
            ]
          }
        },
        "overrides": []
      },
      "gridPos": {
        "h": 6,
        "w": 10,
        "x": 0,
        "y": 10
      },
      "id": 16,
      "options": {
        "colorMode": "value",
        "graphMode": "none",
        "justifyMode": "auto",
        "orientation": "auto",
        "reduceOptions": {
          "calcs": [
            "lastNotNull"
          ],
          "fields": "",
          "values": false
        },
        "textMode": "auto"
      },
      "pluginVersion": "7.3.6",
      "targets": [
        {
          "expr": "avg(rate(awareness_carbon_estimate_calls_timer_bucket{job=\"carbonawareness\", client=\"webapi\"}[$__range]))",
          "interval": "",
          "legendFormat": "Time",
          "refId": "A"
        },
        {
          "expr": "sum(round(increase(awareness_carbon_estimate_calls_timer_count{job=\"carbonawareness\", client=\"webapi\"}[$__range])))",
          "interval": "",
          "legendFormat": "Requests",
          "refId": "B"
        },
        {
          "expr": "sum(round(increase(awareness_carbon_estimate_transactions_total{job=\"carbonawareness\", client=\"webapi\"}[$__range])))",
          "interval": "",
          "legendFormat": "Transactions",
          "refId": "C"
        },
        {
          "expr": "sum(round(increase(awareness_error_types_total{job=\"carbonawareness\", errortype=\"CarbonCalculatorErrorWebApi\"}[$__range])))",
          "interval": "",
          "legendFormat": "Errors",
          "refId": "D"
        }
      ],
      "timeFrom": null,
      "timeShift": null,
      "title": "Web API",
      "type": "stat"
    },
    {
      "datasource": null,
      "description": "",
      "fieldConfig": {
        "defaults": {
          "custom": {},
          "mappings": [],
          "thresholds": {
            "mode": "absolute",
            "steps": [
              {
                "color": "green",
                "value": null
              },
              {
                "color": "red",
                "value": 80
              }
            ]
          }
        },
        "overrides": []
      },
      "gridPos": {
        "h": 6,
        "w": 10,
        "x": 10,
        "y": 10
      },
      "id": 17,
      "options": {
        "colorMode": "value",
        "graphMode": "none",
        "justifyMode": "auto",
        "orientation": "auto",
        "reduceOptions": {
          "calcs": [
            "last"
          ],
          "fields": "",
          "values": false
        },
        "textMode": "auto"
      },
      "pluginVersion": "7.3.6",
      "targets": [
        {
          "expr": "avg(rate(awareness_carbon_estimate_calls_timer_bucket{job=\"carbonawareness\", client=\"grpc\"}[$__range]))",
          "interval": "",
          "legendFormat": "Time",
          "refId": "A"
        },
        {
          "expr": "sum(round(increase(awareness_carbon_estimate_calls_timer_count{job=\"carbonawareness\", client=\"grpc\"}[$__range])))",
          "interval": "",
          "legendFormat": "Requests",
          "refId": "B"
        },
        {
          "expr": "sum(round(increase(awareness_carbon_estimate_transactions_total{job=\"carbonawareness\", client=\"grpc\"}[$__range])))",
          "interval": "",
          "legendFormat": "Transactions",
          "refId": "C"
        },
        {
          "expr": "sum(round(increase(awareness_error_types_total{job=\"carbonawareness\", errortype=\"CarbonCalculatorErrorGrpc\"}[$__range])))",
          "format": "time_series",
          "interval": "",
          "legendFormat": "Errors",
          "refId": "D"
        }
      ],
      "timeFrom": null,
      "timeShift": null,
      "title": "gRPC",
      "type": "stat"
    },
    {
      "datasource": null,
      "fieldConfig": {
        "defaults": {
          "custom": {
            "align": null,
            "filterable": false
          },
          "mappings": [],
          "min": 0,
          "thresholds": {
            "mode": "absolute",
            "steps": [
              {
                "color": "green",
                "value": null
              },
              {
                "color": "red",
                "value": 50
              }
            ]
          }
        },
        "overrides": []
      },
      "gridPos": {
        "h": 2,
        "w": 10,
        "x": 0,
        "y": 16
      },
      "id": 8,
      "interval": "",
      "options": {
        "colorMode": "value",
        "graphMode": "none",
        "justifyMode": "auto",
        "orientation": "auto",
        "reduceOptions": {
          "calcs": [
            "last"
          ],
          "fields": "",
          "values": false
        },
        "textMode": "value"
      },
      "pluginVersion": "7.3.6",
      "targets": [
        {
          "expr": "sum(round(increase(awareness_error_types_total{job=\"carbonawareness\", errortype=\"CarbonCalculatorErrorWebApi\"}[$__range])))",
          "format": "time_series",
          "hide": false,
          "instant": false,
          "interval": "",
          "intervalFactor": 1,
          "legendFormat": "Range",
          "refId": "A"
        }
      ],
      "timeFrom": null,
      "timeShift": null,
      "title": "Web Api Errors",
      "type": "stat"
    },
    {
      "datasource": "-- Mixed --",
      "fieldConfig": {
        "defaults": {
          "custom": {
            "align": null,
            "filterable": false
          },
          "mappings": [],
          "min": 0,
          "thresholds": {
            "mode": "absolute",
            "steps": [
              {
                "color": "green",
                "value": null
              },
              {
                "color": "red",
                "value": 50
              }
            ]
          },
          "unit": "Force"
        },
        "overrides": []
      },
      "gridPos": {
        "h": 2,
        "w": 10,
        "x": 10,
        "y": 16
      },
      "id": 9,
      "interval": "",
      "options": {
        "colorMode": "value",
        "graphMode": "none",
        "justifyMode": "auto",
        "orientation": "auto",
        "reduceOptions": {
          "calcs": [
            "last"
          ],
          "fields": "",
          "values": false
        },
        "textMode": "value"
      },
      "pluginVersion": "7.3.6",
      "targets": [
        {
          "datasource": "Prometheus",
          "expr": "sum(round(increase(awareness_error_types_total{job=\"carbonawareness\", errortype=\"CarbonCalculatorErrorGrpc\"}[$__range])))",
          "format": "time_series",
          "hide": false,
          "instant": false,
          "interval": "",
          "intervalFactor": 1,
          "legendFormat": "Range",
          "refId": "A"
        }
      ],
      "timeFrom": null,
      "timeShift": null,
      "title": "gRPC Errors",
      "type": "stat"
    },
    {
      "aliasColors": {},
      "bars": false,
      "dashLength": 10,
      "dashes": false,
      "datasource": "Prometheus",
      "decimals": 0,
      "description": "",
      "fieldConfig": {
        "defaults": {
          "custom": {},
          "links": []
        },
        "overrides": []
      },
      "fill": 1,
      "fillGradient": 0,
      "gridPos": {
        "h": 8,
        "w": 10,
        "x": 0,
        "y": 18
      },
      "hiddenSeries": false,
      "id": 2,
      "legend": {
        "alignAsTable": true,
        "avg": true,
        "current": true,
        "max": true,
        "min": false,
        "show": true,
        "total": false,
        "values": true
      },
      "lines": true,
      "linewidth": 1,
      "links": [],
      "nullPointMode": "null",
      "options": {
        "alertThreshold": true
      },
      "percentage": false,
      "pluginVersion": "7.3.6",
      "pointradius": 2,
      "points": false,
      "renderer": "flot",
      "seriesOverrides": [],
      "spaceLength": 10,
      "stack": false,
      "steppedLine": false,
      "targets": [
        {
          "expr": "process_num_threads{job=\"carbonawareness\"}",
          "format": "time_series",
          "interval": "",
          "intervalFactor": 1,
          "legendFormat": "{{pod}}",
          "refId": "A"
        }
      ],
      "thresholds": [],
      "timeFrom": null,
      "timeRegions": [],
      "timeShift": null,
      "title": "Number of threads",
      "tooltip": {
        "shared": true,
        "sort": 0,
        "value_type": "individual"
      },
      "type": "graph",
      "xaxis": {
        "buckets": null,
        "mode": "time",
        "name": null,
        "show": true,
        "values": []
      },
      "yaxes": [
        {
          "decimals": 0,
          "format": "short",
          "label": null,
          "logBase": 1,
          "max": null,
          "min": null,
          "show": true
        },
        {
          "format": "short",
          "label": null,
          "logBase": 1,
          "max": null,
          "min": null,
          "show": true
        }
      ],
      "yaxis": {
        "align": false,
        "alignLevel": null
      }
    },
    {
      "aliasColors": {},
      "bars": false,
      "dashLength": 10,
      "dashes": false,
      "datasource": null,
      "fieldConfig": {
        "defaults": {
          "custom": {}
        },
        "overrides": []
      },
      "fill": 1,
      "fillGradient": 0,
      "gridPos": {
        "h": 8,
        "w": 10,
        "x": 10,
        "y": 18
      },
      "hiddenSeries": false,
      "id": 19,
      "legend": {
        "alignAsTable": true,
        "avg": true,
        "current": false,
        "max": true,
        "min": true,
        "rightSide": false,
        "show": true,
        "total": false,
        "values": true
      },
      "lines": true,
      "linewidth": 1,
      "nullPointMode": "null",
      "options": {
        "alertThreshold": true
      },
      "percentage": false,
      "pluginVersion": "7.3.6",
      "pointradius": 2,
      "points": false,
      "renderer": "flot",
      "seriesOverrides": [],
      "spaceLength": 10,
      "stack": false,
      "steppedLine": false,
      "targets": [
        {
          "expr": "process_open_handles{job=\"carbonawareness\"}",
          "interval": "",
          "legendFormat": "{{pod}}",
          "refId": "A"
        }
      ],
      "thresholds": [],
      "timeFrom": null,
      "timeRegions": [],
      "timeShift": null,
      "title": "Open handlers",
      "tooltip": {
        "shared": true,
        "sort": 0,
        "value_type": "individual"
      },
      "type": "graph",
      "xaxis": {
        "buckets": null,
        "mode": "time",
        "name": null,
        "show": true,
        "values": []
      },
      "yaxes": [
        {
          "format": "short",
          "label": null,
          "logBase": 1,
          "max": null,
          "min": null,
          "show": true
        },
        {
          "format": "short",
          "label": null,
          "logBase": 1,
          "max": null,
          "min": null,
          "show": true
        }
      ],
      "yaxis": {
        "align": false,
        "alignLevel": null
      }
    }
  ],
  "refresh": "5s",
  "schemaVersion": 26,
  "style": "dark",
  "tags": [],
  "templating": {
    "list": []
  },
  "time": {
    "from": "now-15m",
    "to": "now"
  },
  "timepicker": {},
  "timezone": "",
  "title": "Calculator Client A/B testing",
  "uid": "4e_XpVeMk",
  "version": 1
}