{
  "annotations": {
    "list": [
      {
        "builtIn": 1,
        "datasource": "-- Grafana --",
        "enable": true,
        "hide": true,
        "iconColor": "rgba(0, 211, 255, 1)",
        "name": "Annotations & Alerts",
        "type": "dashboard"
      }
    ]
  },
  "editable": true,
  "gnetId": null,
  "graphTooltip": 0,
  "links": [],
  "panels": [
    {
      "aliasColors": {
        "Duplicates": "light-red",
        "New": "green",
        "No longer occurring": "red",
        "Total detected patterns": "blue",
        "Updated": "orange"
      },
      "bars": false,
      "dashLength": 10,
      "dashes": false,
      "datasource": "AppMetrics",
      "description": "",
      "fieldConfig": {
        "defaults": {
          "custom": {},
          "links": []
        },
        "overrides": []
      },
      "fill": 1,
      "fillGradient": 0,
      "gridPos": {
        "h": 8,
        "w": 12,
        "x": 0,
        "y": 0
      },
      "hiddenSeries": false,
      "id": 13,
      "legend": {
        "avg": false,
        "current": false,
        "max": false,
        "min": false,
        "show": true,
        "total": false,
        "values": false
      },
      "lines": true,
      "linewidth": 1,
      "nullPointMode": "null",
      "options": {
        "alertThreshold": true
      },
      "percentage": false,
      "pluginVersion": "7.3.6",
      "pointradius": 2,
      "points": false,
      "renderer": "flot",
      "seriesOverrides": [
        {
          "alias": "PatternDetectedEventHandler.Time.mean",
          "yaxis": 2
        },
        {
          "alias": "Time (ms)",
          "yaxis": 2
        }
      ],
      "spaceLength": 10,
      "stack": false,
      "steppedLine": false,
      "targets": [
        {
          "alias": "Total detected patterns",
          "groupBy": [
            {
              "params": [
                "$__interval"
              ],
              "type": "time"
            },
            {
              "params": [
                "null"
              ],
              "type": "fill"
            }
          ],
          "measurement": "PatternDetectedEventHandler.Detected.Total",
          "orderByTime": "ASC",
          "policy": "default",
          "refId": "A",
          "resultFormat": "time_series",
          "select": [
            [
              {
                "params": [
                  "value"
                ],
                "type": "field"
              },
              {
                "params": [],
                "type": "sum"
              }
            ]
          ],
          "tags": []
        },
        {
          "alias": "New",
          "groupBy": [
            {
              "params": [
                "$__interval"
              ],
              "type": "time"
            },
            {
              "params": [
                "null"
              ],
              "type": "fill"
            }
          ],
          "measurement": "PatternDetectedEventHandler.Detected.New",
          "orderByTime": "ASC",
          "policy": "default",
          "refId": "B",
          "resultFormat": "time_series",
          "select": [
            [
              {
                "params": [
                  "value"
                ],
                "type": "field"
              },
              {
                "params": [],
                "type": "sum"
              }
            ]
          ],
          "tags": []
        },
        {
          "alias": "Updated",
          "groupBy": [
            {
              "params": [
                "$__interval"
              ],
              "type": "time"
            },
            {
              "params": [
                "null"
              ],
              "type": "fill"
            }
          ],
          "measurement": "PatternDetectedEventHandler.Detected.Update",
          "orderByTime": "ASC",
          "policy": "default",
          "refId": "E",
          "resultFormat": "time_series",
          "select": [
            [
              {
                "params": [
                  "value"
                ],
                "type": "field"
              },
              {
                "params": [],
                "type": "sum"
              }
            ]
          ],
          "tags": []
        },
        {
          "alias": "No longer occurring",
          "groupBy": [
            {
              "params": [
                "$__interval"
              ],
              "type": "time"
            },
            {
              "params": [
                "null"
              ],
              "type": "fill"
            }
          ],
          "measurement": "PatternDetectedEventHandler.Detected.NoLongerOccurring",
          "orderByTime": "ASC",
          "policy": "default",
          "refId": "C",
          "resultFormat": "time_series",
          "select": [
            [
              {
                "params": [
                  "value"
                ],
                "type": "field"
              },
              {
                "params": [],
                "type": "sum"
              }
            ]
          ],
          "tags": []
        },
        {
          "alias": "Duplicates",
          "groupBy": [
            {
              "params": [
                "$__interval"
              ],
              "type": "time"
            },
            {
              "params": [
                "null"
              ],
              "type": "fill"
            }
          ],
          "measurement": "PatternDetectedEventHandler.Detected.Duplicates",
          "orderByTime": "ASC",
          "policy": "default",
          "refId": "D",
          "resultFormat": "time_series",
          "select": [
            [
              {
                "params": [
                  "value"
                ],
                "type": "field"
              },
              {
                "params": [],
                "type": "sum"
              }
            ]
          ],
          "tags": []
        },
        {
          "alias": "Time (ms)",
          "groupBy": [
            {
              "params": [
                "$__interval"
              ],
              "type": "time"
            },
            {
              "params": [
                "null"
              ],
              "type": "fill"
            }
          ],
          "measurement": "PatternDetectedEventHandler.Time",
          "orderByTime": "ASC",
          "policy": "default",
          "refId": "F",
          "resultFormat": "time_series",
          "select": [
            [
              {
                "params": [
                  "value"
                ],
                "type": "field"
              },
              {
                "params": [],
                "type": "mean"
              }
            ]
          ],
          "tags": []
        }
      ],
      "thresholds": [],
      "timeFrom": null,
      "timeRegions": [],
      "timeShift": null,
      "title": "Pattern detection",
      "tooltip": {
        "shared": true,
        "sort": 0,
        "value_type": "individual"
      },
      "type": "graph",
      "xaxis": {
        "buckets": null,
        "mode": "time",
        "name": null,
        "show": true,
        "values": []
      },
      "yaxes": [
        {
          "format": "short",
          "label": null,
          "logBase": 1,
          "max": null,
          "min": null,
          "show": true
        },
        {
          "format": "short",
          "label": null,
          "logBase": 1,
          "max": null,
          "min": null,
          "show": true
        }
      ],
      "yaxis": {
        "align": false,
        "alignLevel": null
      }
    },
    {
      "cacheTimeout": null,
      "colorBackground": false,
      "colorPostfix": true,
      "colorPrefix": false,
      "colorValue": true,
      "colors": [
        "#d44a3a",
        "#73BF69",
        "#299c46"
      ],
      "datasource": "AppMetrics",
      "decimals": null,
      "fieldConfig": {
        "defaults": {
          "custom": {}
        },
        "overrides": []
      },
      "format": "none",
      "gauge": {
        "maxValue": 100,
        "minValue": 0,
        "show": false,
        "thresholdLabels": false,
        "thresholdMarkers": true
      },
      "gridPos": {
        "h": 8,
        "w": 6,
        "x": 12,
        "y": 0
      },
      "id": 17,
      "interval": null,
      "links": [],
      "mappingType": 1,
      "mappingTypes": [
        {
          "name": "value to text",
          "value": 1
        },
        {
          "name": "range to text",
          "value": 2
        }
      ],
      "maxDataPoints": 100,
      "nullPointMode": "connected",
      "nullText": null,
      "postfix": " new patterns",
      "postfixFontSize": "50%",
      "prefix": "",
      "prefixFontSize": "50%",
      "rangeMaps": [
        {
          "from": "null",
          "text": "N/A",
          "to": "null"
        }
      ],
      "sparkline": {
        "fillColor": "rgba(31, 118, 189, 0.18)",
        "full": false,
        "lineColor": "rgb(31, 120, 193)",
        "show": true,
        "ymax": null,
        "ymin": null
      },
      "tableColumn": "",
      "targets": [
        {
          "groupBy": [
            {
              "params": [
                "$__interval"
              ],
              "type": "time"
            },
            {
              "params": [
                "null"
              ],
              "type": "fill"
            }
          ],
          "measurement": "PatternDetectedEventHandler.Detected.New",
          "orderByTime": "ASC",
          "policy": "default",
          "refId": "A",
          "resultFormat": "time_series",
          "select": [
            [
              {
                "params": [
                  "value"
                ],
                "type": "field"
              },
              {
                "params": [],
                "type": "sum"
              }
            ]
          ],
          "tags": []
        }
      ],
      "thresholds": "0,1",
      "timeFrom": null,
      "timeShift": null,
      "title": "New detected patterns",
      "type": "singlestat",
      "valueFontSize": "80%",
      "valueMaps": [
        {
          "op": "=",
          "text": "N/A",
          "value": "null"
        }
      ],
      "valueName": "total"
    },
    {
      "cacheTimeout": null,
      "colorBackground": false,
      "colorPostfix": false,
      "colorValue": false,
      "colors": [
        "#d44a3a",
        "rgba(237, 129, 40, 0.89)",
        "#299c46"
      ],
      "datasource": "AppMetrics",
      "fieldConfig": {
        "defaults": {
          "custom": {}
        },
        "overrides": []
      },
      "format": "none",
      "gauge": {
        "maxValue": 100,
        "minValue": 0,
        "show": false,
        "thresholdLabels": false,
        "thresholdMarkers": true
      },
      "gridPos": {
        "h": 8,
        "w": 6,
        "x": 18,
        "y": 0
      },
      "id": 18,
      "interval": null,
      "links": [],
      "mappingType": 1,
      "mappingTypes": [
        {
          "name": "value to text",
          "value": 1
        },
        {
          "name": "range to text",
          "value": 2
        }
      ],
      "maxDataPoints": 100,
      "nullPointMode": "connected",
      "nullText": null,
      "postfix": " No longer occurring",
      "postfixFontSize": "50%",
      "prefix": "",
      "prefixFontSize": "50%",
      "rangeMaps": [
        {
          "from": "null",
          "text": "N/A",
          "to": "null"
        }
      ],
      "sparkline": {
        "fillColor": "rgba(31, 118, 189, 0.18)",
        "full": false,
        "lineColor": "#F2495C",
        "show": true,
        "ymax": null,
        "ymin": null
      },
      "tableColumn": "",
      "targets": [
        {
          "groupBy": [
            {
              "params": [
                "$__interval"
              ],
              "type": "time"
            },
            {
              "params": [
                "null"
              ],
              "type": "fill"
            }
          ],
          "measurement": "PatternDetectedEventHandler.Detected.NoLongerOccurring",
          "orderByTime": "ASC",
          "policy": "default",
          "refId": "A",
          "resultFormat": "time_series",
          "select": [
            [
              {
                "params": [
                  "value"
                ],
                "type": "field"
              },
              {
                "params": [],
                "type": "sum"
              }
            ]
          ],
          "tags": []
        }
      ],
      "thresholds": "",
      "timeFrom": null,
      "timeShift": null,
      "title": "No longer occurring patterns",
      "type": "singlestat",
      "valueFontSize": "80%",
      "valueMaps": [
        {
          "op": "=",
          "text": "N/A",
          "value": "null"
        }
      ],
      "valueName": "total"
    },
    {
      "aliasColors": {
        "Reconcile suggestions": "light-orange",
        "Reconciled transactions": "light-blue"
      },
      "bars": false,
      "dashLength": 10,
      "dashes": false,
      "datasource": "AppMetrics",
      "description": "",
      "fieldConfig": {
        "defaults": {
          "custom": {},
          "links": []
        },
        "overrides": []
      },
      "fill": 1,
      "fillGradient": 0,
      "gridPos": {
        "h": 8,
        "w": 12,
        "x": 0,
        "y": 8
      },
      "hiddenSeries": false,
      "id": 22,
      "legend": {
        "alignAsTable": false,
        "avg": false,
        "current": false,
        "hideEmpty": false,
        "max": true,
        "min": false,
        "show": true,
        "total": false,
        "values": true
      },
      "lines": true,
      "linewidth": 1,
      "nullPointMode": "null",
      "options": {
        "alertThreshold": true
      },
      "percentage": false,
      "pluginVersion": "7.3.6",
      "pointradius": 2,
      "points": false,
      "renderer": "flot",
      "seriesOverrides": [
        {
          "alias": "Average confidence score (reconciled)",
          "yaxis": 2
        }
      ],
      "spaceLength": 10,
      "stack": false,
      "steppedLine": false,
      "targets": [
        {
          "alias": "Reconciled transactions",
          "groupBy": [
            {
              "params": [
                "1d"
              ],
              "type": "time"
            },
            {
              "params": [
                "null"
              ],
              "type": "fill"
            }
          ],
          "measurement": "ReconciliationService.Reconciled.Transactions",
          "orderByTime": "ASC",
          "policy": "default",
          "refId": "A",
          "resultFormat": "time_series",
          "select": [
            [
              {
                "params": [
                  "value"
                ],
                "type": "field"
              },
              {
                "params": [],
                "type": "count"
              }
            ]
          ],
          "tags": []
        },
        {
          "alias": "Reconcile suggestions",
          "groupBy": [
            {
              "params": [
                "1d"
              ],
              "type": "time"
            },
            {
              "params": [
                "null"
              ],
              "type": "fill"
            }
          ],
          "measurement": "ReconciliationService.Suggestions",
          "orderByTime": "ASC",
          "policy": "default",
          "refId": "B",
          "resultFormat": "time_series",
          "select": [
            [
              {
                "params": [
                  "value"
                ],
                "type": "field"
              },
              {
                "params": [],
                "type": "count"
              }
            ]
          ],
          "tags": []
        },
        {
          "alias": "Average confidence score (reconciled)",
          "groupBy": [
            {
              "params": [
                "$__interval"
              ],
              "type": "time"
            },
            {
              "params": [
                "null"
              ],
              "type": "fill"
            }
          ],
          "measurement": "ReconciliationQuality",
          "orderByTime": "ASC",
          "policy": "default",
          "refId": "C",
          "resultFormat": "time_series",
          "select": [
            [
              {
                "params": [
                  "AvgConfidenceScore"
                ],
                "type": "field"
              },
              {
                "params": [],
                "type": "mean"
              }
            ]
          ],
          "tags": []
        }
      ],
      "thresholds": [],
      "timeFrom": null,
      "timeRegions": [],
      "timeShift": null,
      "title": "Reconciliation Suggested/Accepted Count (per day)",
      "tooltip": {
        "shared": true,
        "sort": 0,
        "value_type": "individual"
      },
      "type": "graph",
      "xaxis": {
        "buckets": null,
        "mode": "time",
        "name": null,
        "show": true,
        "values": []
      },
      "yaxes": [
        {
          "format": "short",
          "label": null,
          "logBase": 1,
          "max": null,
          "min": null,
          "show": true
        },
        {
          "format": "short",
          "label": null,
          "logBase": 1,
          "max": null,
          "min": null,
          "show": true
        }
      ],
      "yaxis": {
        "align": false,
        "alignLevel": null
      }
    },
    {
      "cacheTimeout": null,
      "colorBackground": false,
      "colorPostfix": true,
      "colorPrefix": false,
      "colorValue": true,
      "colors": [
        "#d44a3a",
        "#73BF69",
        "#299c46"
      ],
      "datasource": "AppMetrics",
      "decimals": null,
      "fieldConfig": {
        "defaults": {
          "custom": {}
        },
        "overrides": []
      },
      "format": "none",
      "gauge": {
        "maxValue": 100,
        "minValue": 0,
        "show": false,
        "thresholdLabels": false,
        "thresholdMarkers": true
      },
      "gridPos": {
        "h": 8,
        "w": 6,
        "x": 12,
        "y": 8
      },
      "id": 19,
      "interval": null,
      "links": [],
      "mappingType": 1,
      "mappingTypes": [
        {
          "name": "value to text",
          "value": 1
        },
        {
          "name": "range to text",
          "value": 2
        }
      ],
      "maxDataPoints": 100,
      "nullPointMode": "connected",
      "nullText": null,
      "postfix": " reconciled transactions",
      "postfixFontSize": "50%",
      "prefix": "",
      "prefixFontSize": "50%",
      "rangeMaps": [
        {
          "from": "null",
          "text": "N/A",
          "to": "null"
        }
      ],
      "sparkline": {
        "fillColor": "rgba(31, 118, 189, 0.18)",
        "full": false,
        "lineColor": "rgb(31, 120, 193)",
        "show": true,
        "ymax": null,
        "ymin": null
      },
      "tableColumn": "",
      "targets": [
        {
          "groupBy": [
            {
              "params": [
                "$__interval"
              ],
              "type": "time"
            },
            {
              "params": [
                "null"
              ],
              "type": "fill"
            }
          ],
          "measurement": "ReconciliationService.Reconciled.Transactions",
          "orderByTime": "ASC",
          "policy": "default",
          "refId": "A",
          "resultFormat": "time_series",
          "select": [
            [
              {
                "params": [
                  "value"
                ],
                "type": "field"
              },
              {
                "params": [],
                "type": "sum"
              }
            ]
          ],
          "tags": []
        }
      ],
      "thresholds": "0,1",
      "timeFrom": null,
      "timeShift": null,
      "title": "Reconciled transactions",
      "type": "singlestat",
      "valueFontSize": "80%",
      "valueMaps": [
        {
          "op": "=",
          "text": "N/A",
          "value": "null"
        }
      ],
      "valueName": "total"
    },
    {
      "cacheTimeout": null,
      "colorBackground": false,
      "colorPostfix": true,
      "colorPrefix": false,
      "colorValue": true,
      "colors": [
        "#d44a3a",
        "#73BF69",
        "#299c46"
      ],
      "datasource": "AppMetrics",
      "decimals": null,
      "fieldConfig": {
        "defaults": {
          "custom": {}
        },
        "overrides": []
      },
      "format": "none",
      "gauge": {
        "maxValue": 100,
        "minValue": 0,
        "show": false,
        "thresholdLabels": false,
        "thresholdMarkers": true
      },
      "gridPos": {
        "h": 8,
        "w": 6,
        "x": 18,
        "y": 8
      },
      "id": 20,
      "interval": null,
      "links": [],
      "mappingType": 1,
      "mappingTypes": [
        {
          "name": "value to text",
          "value": 1
        },
        {
          "name": "range to text",
          "value": 2
        }
      ],
      "maxDataPoints": 100,
      "nullPointMode": "connected",
      "nullText": null,
      "postfix": " reconciliation suggestions",
      "postfixFontSize": "50%",
      "prefix": "",
      "prefixFontSize": "50%",
      "rangeMaps": [
        {
          "from": "null",
          "text": "N/A",
          "to": "null"
        }
      ],
      "sparkline": {
        "fillColor": "rgba(31, 118, 189, 0.18)",
        "full": false,
        "lineColor": "rgb(31, 120, 193)",
        "show": true,
        "ymax": null,
        "ymin": null
      },
      "tableColumn": "",
      "targets": [
        {
          "groupBy": [
            {
              "params": [
                "$__interval"
              ],
              "type": "time"
            },
            {
              "params": [
                "null"
              ],
              "type": "fill"
            }
          ],
          "measurement": "ReconciliationService.Suggestions",
          "orderByTime": "ASC",
          "policy": "default",
          "refId": "A",
          "resultFormat": "time_series",
          "select": [
            [
              {
                "params": [
                  "value"
                ],
                "type": "field"
              },
              {
                "params": [],
                "type": "sum"
              }
            ]
          ],
          "tags": []
        }
      ],
      "thresholds": "0,1",
      "timeFrom": null,
      "timeShift": null,
      "title": "Reconciliation suggestions",
      "type": "singlestat",
      "valueFontSize": "80%",
      "valueMaps": [
        {
          "op": "=",
          "text": "N/A",
          "value": "null"
        }
      ],
      "valueName": "total"
    },
    {
      "columns": [],
      "datasource": "AppMetrics",
      "description": "Based on daily query of various metrics gathered directly from the database",
      "fieldConfig": {
        "defaults": {
          "custom": {}
        },
        "overrides": []
      },
      "fontSize": "100%",
      "gridPos": {
        "h": 8,
        "w": 24,
        "x": 0,
        "y": 16
      },
      "id": 24,
      "pageSize": null,
      "scroll": true,
      "showHeader": true,
      "sort": {
        "col": 0,
        "desc": true
      },
      "styles": [
        {
          "alias": "Time",
          "align": "auto",
          "dateFormat": "YYYY-MM-DD HH:mm:ss",
          "pattern": "Time",
          "type": "hidden"
        },
        {
          "alias": "",
          "align": "auto",
          "colorMode": "cell",
          "colors": [
            "rgba(50, 172, 45, 0)",
            "rgba(237, 129, 40, 0.89)",
            "rgba(245, 54, 54, 0.9)"
          ],
          "dateFormat": "YYYY-MM-DD HH:mm:ss",
          "decimals": 2,
          "link": false,
          "mappingType": 1,
          "pattern": "AvgDayDifference",
          "thresholds": [
            "3",
            "5"
          ],
          "type": "number",
          "unit": "short"
        },
        {
          "alias": "",
          "align": "auto",
          "colorMode": "cell",
          "colors": [
            "rgba(50, 172, 45, 0)",
            "rgba(237, 129, 40, 0.89)",
            "rgba(245, 54, 54, 0.9)"
          ],
          "dateFormat": "YYYY-MM-DD HH:mm:ss",
          "decimals": 2,
          "mappingType": 1,
          "pattern": "AvgAmountDifference",
          "thresholds": [
            "5000",
            "1000"
          ],
          "type": "number",
          "unit": "short"
        },
        {
          "alias": "",
          "align": "auto",
          "colorMode": "cell",
          "colors": [
            "rgba(245, 54, 54, 0.9)",
            "rgba(237, 129, 40, 0.89)",
            "rgba(50, 172, 45, 0)"
          ],
          "dateFormat": "YYYY-MM-DD HH:mm:ss",
          "decimals": 4,
          "mappingType": 1,
          "pattern": "AvgConfidenceScore",
          "thresholds": [
            "0.97",
            "0.98"
          ],
          "type": "number",
          "unit": "short"
        },
        {
          "alias": "",
          "align": "auto",
          "colorMode": "cell",
          "colors": [
            "rgba(50, 172, 45, 0)",
            "rgba(237, 129, 40, 0.89)",
            "rgba(245, 54, 54, 0.9)"
          ],
          "dateFormat": "YYYY-MM-DD HH:mm:ss",
          "decimals": 2,
          "mappingType": 1,
          "pattern": "AvgLeveshteinDifference",
          "thresholds": [
            "2",
            "4"
          ],
          "type": "number",
          "unit": "short"
        },
        {
          "alias": "",
          "align": "auto",
          "colorMode": "cell",
          "colors": [
            "rgba(50, 172, 45, 0)",
            "rgba(237, 129, 40, 0.89)",
            "rgba(245, 54, 54, 0.9)"
          ],
          "dateFormat": "YYYY-MM-DD HH:mm:ss",
          "decimals": 2,
          "mappingType": 1,
          "pattern": "TotalInDifferentCurrency",
          "thresholds": [
            "1",
            "2"
          ],
          "type": "number",
          "unit": "short"
        },
        {
          "alias": "",
          "align": "auto",
          "colorMode": "cell",
          "colors": [
            "rgba(50, 172, 45, 0.97)",
            "rgba(237, 129, 40, 0.89)",
            "rgba(245, 54, 54, 0.9)"
          ],
          "dateFormat": "YYYY-MM-DD HH:mm:ss",
          "decimals": 2,
          "mappingType": 1,
          "pattern": "MaxAmountDifference",
          "thresholds": [
            "1000",
            "2000"
          ],
          "type": "number",
          "unit": "short"
        },
        {
          "alias": "",
          "align": "auto",
          "colorMode": null,
          "colors": [
            "rgba(245, 54, 54, 0.9)",
            "rgba(237, 129, 40, 0.89)",
            "rgba(50, 172, 45, 0.97)"
          ],
          "decimals": 2,
          "pattern": "/.*/",
          "thresholds": [],
          "type": "number",
          "unit": "short"
        }
      ],
      "targets": [
        {
          "alias": "Average day difference",
          "groupBy": [
            {
              "params": [
                "1h"
              ],
              "type": "time"
            },
            {
              "params": [
                "none"
              ],
              "type": "fill"
            }
          ],
          "measurement": "ReconciliationQuality",
          "orderByTime": "ASC",
          "policy": "default",
          "query": "SELECT first(\"dateFrom\") AS \"DateFrom\", first(\"dateTo\") AS \"DateTo\", mean(\"AvgDayDifference\") AS \"AvgDayDifference\", mean(\"AvgAmountDifference\") AS \"AvgAmountDifference\", max(\"MaxAmountDifference\") AS \"MaxAmountDifference\", mean(\"AvgConfidenceScore\") AS \"AvgConfidenceScore\", mean(\"AvgLevenshteinDifference\") AS \"AvgLeveshteinDifference\", sum(\"TotalDifferentCurrency\") AS \"TotalInDifferentCurrency\" FROM \"ReconciliationQuality\" WHERE $timeFilter GROUP BY time(1h) fill(none)",
          "rawQuery": true,
          "refId": "A",
          "resultFormat": "table",
          "select": [
            [
              {
                "params": [
                  "AvgDayDifference"
                ],
                "type": "field"
              },
              {
                "params": [],
                "type": "first"
              },
              {
                "params": [
                  "AvgDayDifference"
                ],
                "type": "alias"
              }
            ],
            [
              {
                "params": [
                  "AvgAmountDifference"
                ],
                "type": "field"
              },
              {
                "params": [],
                "type": "first"
              },
              {
                "params": [
                  "AvgAmountDifference"
                ],
                "type": "alias"
              }
            ],
            [
              {
                "params": [
                  "AvgConfidenceScore"
                ],
                "type": "field"
              },
              {
                "params": [],
                "type": "first"
              },
              {
                "params": [
                  "AvgConfidenceScore"
                ],
                "type": "alias"
              }
            ],
            [
              {
                "params": [
                  "AvgLevenshteinDifference"
                ],
                "type": "field"
              },
              {
                "params": [],
                "type": "first"
              },
              {
                "params": [
                  "LeveshteinDifference"
                ],
                "type": "alias"
              }
            ],
            [
              {
                "params": [
                  "TotalDifferentCurrency"
                ],
                "type": "field"
              },
              {
                "params": [],
                "type": "first"
              },
              {
                "params": [
                  "TotalInDifferentCurrency"
                ],
                "type": "alias"
              }
            ],
            [
              {
                "params": [
                  "MaxAmountDifference"
                ],
                "type": "field"
              },
              {
                "params": [],
                "type": "first"
              },
              {
                "params": [
                  "MaxAmountDifference"
                ],
                "type": "alias"
              }
            ]
          ],
          "tags": []
        }
      ],
      "timeFrom": null,
      "timeShift": null,
      "title": "Reconciliation metrics",
      "transform": "table",
      "type": "table-old"
    },
    {
      "cacheTimeout": null,
      "colorBackground": false,
      "colorPostfix": true,
      "colorValue": true,
      "colors": [
        "#F2495C",
        "rgba(237, 129, 40, 0.89)",
        "#d44a3a"
      ],
      "datasource": "AppMetrics",
      "fieldConfig": {
        "defaults": {
          "custom": {}
        },
        "overrides": []
      },
      "format": "none",
      "gauge": {
        "maxValue": 100,
        "minValue": 0,
        "show": false,
        "thresholdLabels": false,
        "thresholdMarkers": true
      },
      "gridPos": {
        "h": 7,
        "w": 6,
        "x": 0,
        "y": 24
      },
      "id": 10,
      "interval": null,
      "links": [],
      "mappingType": 1,
      "mappingTypes": [
        {
          "name": "value to text",
          "value": 1
        },
        {
          "name": "range to text",
          "value": 2
        }
      ],
      "maxDataPoints": 100,
      "nullPointMode": "connected",
      "nullText": null,
      "postfix": " rejected patterns",
      "postfixFontSize": "50%",
      "prefix": "",
      "prefixFontSize": "50%",
      "rangeMaps": [
        {
          "from": "null",
          "text": "N/A",
          "to": "null"
        }
      ],
      "sparkline": {
        "fillColor": "rgba(31, 118, 189, 0.18)",
        "full": true,
        "lineColor": "rgb(31, 120, 193)",
        "show": true,
        "ymax": null,
        "ymin": null
      },
      "tableColumn": "",
      "targets": [
        {
          "alias": "Reject Pattern",
          "groupBy": [
            {
              "params": [
                "$__interval"
              ],
              "type": "time"
            },
            {
              "params": [
                "null"
              ],
              "type": "fill"
            }
          ],
          "measurement": "UpcomingRecurringPatternController.DeleteRecurring",
          "orderByTime": "ASC",
          "policy": "default",
          "refId": "A",
          "resultFormat": "time_series",
          "select": [
            [
              {
                "params": [
                  "value"
                ],
                "type": "field"
              },
              {
                "params": [],
                "type": "count"
              }
            ]
          ],
          "tags": []
        }
      ],
      "thresholds": "",
      "timeFrom": null,
      "timeShift": null,
      "title": "Rejected Patterns in Time range",
      "type": "singlestat",
      "valueFontSize": "80%",
      "valueMaps": [
        {
          "op": "=",
          "text": "N/A",
          "value": "null"
        }
      ],
      "valueName": "total"
    },
    {
      "cacheTimeout": null,
      "colorBackground": false,
      "colorPostfix": true,
      "colorValue": true,
      "colors": [
        "#73BF69",
        "rgba(237, 129, 40, 0.89)",
        "#d44a3a"
      ],
      "datasource": "AppMetrics",
      "fieldConfig": {
        "defaults": {
          "custom": {}
        },
        "overrides": []
      },
      "format": "none",
      "gauge": {
        "maxValue": 100,
        "minValue": 0,
        "show": false,
        "thresholdLabels": false,
        "thresholdMarkers": true
      },
      "gridPos": {
        "h": 7,
        "w": 6,
        "x": 6,
        "y": 24
      },
      "id": 11,
      "interval": null,
      "links": [],
      "mappingType": 1,
      "mappingTypes": [
        {
          "name": "value to text",
          "value": 1
        },
        {
          "name": "range to text",
          "value": 2
        }
      ],
      "maxDataPoints": 100,
      "nullPointMode": "connected",
      "nullText": null,
      "postfix": "accepted patterns",
      "postfixFontSize": "50%",
      "prefix": "",
      "prefixFontSize": "50%",
      "rangeMaps": [
        {
          "from": "null",
          "text": "N/A",
          "to": "null"
        }
      ],
      "sparkline": {
        "fillColor": "rgba(31, 118, 189, 0.18)",
        "full": true,
        "lineColor": "rgb(31, 120, 193)",
        "show": true,
        "ymax": null,
        "ymin": null
      },
      "tableColumn": "",
      "targets": [
        {
          "alias": "Accept Pattern",
          "groupBy": [
            {
              "params": [
                "$__interval"
              ],
              "type": "time"
            },
            {
              "params": [
                "null"
              ],
              "type": "fill"
            }
          ],
          "measurement": "UpcomingRecurringPatternController.AcceptRecurring",
          "orderByTime": "ASC",
          "policy": "default",
          "refId": "A",
          "resultFormat": "time_series",
          "select": [
            [
              {
                "params": [
                  "value"
                ],
                "type": "field"
              },
              {
                "params": [],
                "type": "count"
              }
            ]
          ],
          "tags": []
        }
      ],
      "thresholds": "",
      "timeFrom": null,
      "timeShift": null,
      "title": "Accepted Patterns in Time range",
      "type": "singlestat",
      "valueFontSize": "80%",
      "valueMaps": [
        {
          "op": "=",
          "text": "N/A",
          "value": "null"
        }
      ],
      "valueName": "total"
    },
    {
      "cacheTimeout": null,
      "colorBackground": false,
      "colorPostfix": false,
      "colorPrefix": false,
      "colorValue": false,
      "colors": [
        "#299c46",
        "rgba(237, 129, 40, 0.89)",
        "#d44a3a"
      ],
      "datasource": "AppMetrics",
      "decimals": null,
      "fieldConfig": {
        "defaults": {
          "custom": {}
        },
        "overrides": []
      },
      "format": "none",
      "gauge": {
        "maxValue": 100,
        "minValue": 0,
        "show": false,
        "thresholdLabels": false,
        "thresholdMarkers": true
      },
      "gridPos": {
        "h": 7,
        "w": 7,
        "x": 12,
        "y": 24
      },
      "id": 5,
      "interval": null,
      "links": [],
      "mappingType": 1,
      "mappingTypes": [
        {
          "name": "value to text",
          "value": 1
        },
        {
          "name": "range to text",
          "value": 2
        }
      ],
      "maxDataPoints": 100,
      "nullPointMode": "connected",
      "nullText": null,
      "pluginVersion": "6.4.2",
      "postfix": " manual upcomings",
      "postfixFontSize": "50%",
      "prefix": "",
      "prefixFontSize": "50%",
      "rangeMaps": [
        {
          "from": "null",
          "text": "N/A",
          "to": "null"
        }
      ],
      "sparkline": {
        "fillColor": "rgba(31, 118, 189, 0.18)",
        "full": true,
        "lineColor": "rgb(31, 120, 193)",
        "show": true,
        "ymax": null,
        "ymin": null
      },
      "tableColumn": "",
      "targets": [
        {
          "groupBy": [
            {
              "params": [
                "$__interval"
              ],
              "type": "time"
            },
            {
              "params": [
                "null"
              ],
              "type": "fill"
            }
          ],
          "measurement": "UpcomingCrudController.CreateUpcoming",
          "orderByTime": "ASC",
          "policy": "default",
          "refId": "A",
          "resultFormat": "time_series",
          "select": [
            [
              {
                "params": [
                  "value"
                ],
                "type": "field"
              },
              {
                "params": [],
                "type": "count"
              }
            ]
          ],
          "tags": []
        }
      ],
      "thresholds": "",
      "timeFrom": null,
      "timeShift": null,
      "title": "Created manual upcomings in Time range",
      "type": "singlestat",
      "valueFontSize": "80%",
      "valueMaps": [
        {
          "op": "=",
          "text": "N/A",
          "value": "null"
        }
      ],
      "valueName": "total"
    }
  ],
  "refresh": "1d",
  "schemaVersion": 26,
  "style": "dark",
  "tags": [
    "cashflowassistant"
  ],
  "templating": {
    "list": []
  },
  "time": {
    "from": "now-7d",
    "to": "now"
  },
  "timepicker": {
    "refresh_intervals": [
      "1d"
    ]
  },
  "timezone": "",
  "title": "Cashflow Assistant Business Metrics",
  "uid": "ffFE30AWk",
  "version": 24
}